langbase/__init__.py
langbase/constants.py
langbase/errors.py
langbase/helper.py
langbase/langbase.py
langbase/request.py
langbase/streaming.py
langbase/types.py
langbase/utils.py
langbase/workflow.py
langbase/primitives/agent.py
langbase/primitives/chunker.py
langbase/primitives/embed.py
langbase/primitives/images.py
langbase/primitives/memories.py
langbase/primitives/parser.py
langbase/primitives/pipes.py
langbase/primitives/threads.py
langbase/primitives/tools.py
langbase-0.0.5.dist-info/licenses/LICENCE
langbase-0.0.5.dist-info/METADATA
langbase-0.0.5.dist-info/WHEEL
langbase-0.0.5.dist-info/top_level.txt
langbase-0.0.5.dist-info/RECORD
