Metadata-Version: 2.4
Name: langbase
Version: 0.0.5
Summary: Python SDK for the Langbase API
Author-email: Ahmad Awais <aa@ahmadawais.com>, Ahmad Bilal <bilal@langbase.com>, Ashar Irfan <ashar@langbase.com>, Saad Irfan <saad@langbase.com>, Ankit Kumar <ankit@langbase.com>, Saqib Ameen <saqib@langbase.com>
License-Expression: Apache-2.0
Project-URL: Documentation, https://docs.langbase.com
Project-URL: Homepage, https://langbase.com
Project-URL: Repository, https://github.com/LangbaseInc/langbase-python-sdk
Project-URL: Issues, https://github.com/LangbaseInc/langbase-python-sdk/issues
Keywords: ai,langbase,agent,memory,rag,mcp,pipes,workflow,llms
Classifier: Intended Audience :: Developers
Classifier: Operating System :: OS Independent
Classifier: Programming Language :: Python :: 3
Classifier: Programming Language :: Python :: 3.7
Classifier: Programming Language :: Python :: 3.8
Classifier: Programming Language :: Python :: 3.9
Classifier: Programming Language :: Python :: 3.10
Classifier: Programming Language :: Python :: 3.11
Classifier: Programming Language :: Python :: 3.12
Classifier: Programming Language :: Python :: 3 :: Only
Classifier: Topic :: Scientific/Engineering :: Artificial Intelligence
Classifier: Topic :: Software Development :: Libraries :: Python Modules
Requires-Python: >=3.7
License-File: LICENCE
Requires-Dist: requests>=2.25.0
Requires-Dist: typing-extensions>=4.0.0
Dynamic: license-file
